playwright_server/__init__.py
playwright_server/server.py
playwright_server-0.2.1.dist-info/METADATA
playwright_server-0.2.1.dist-info/WHEEL
playwright_server-0.2.1.dist-info/entry_points.txt
playwright_server-0.2.1.dist-info/licenses/LICENSE
playwright_server-0.2.1.dist-info/RECORD
